azure/communication/sms/__init__.py
azure/communication/sms/_sms_client.py
azure/communication/sms/_version.py
azure/communication/sms/py.typed
azure/communication/sms/_generated/__init__.py
azure/communication/sms/_generated/_azure_communication_sms_service.py
azure/communication/sms/_generated/_configuration.py
azure/communication/sms/_generated/py.typed
azure/communication/sms/_generated/aio/__init__.py
azure/communication/sms/_generated/aio/_azure_communication_sms_service.py
azure/communication/sms/_generated/aio/_configuration.py
azure/communication/sms/_generated/aio/operations/__init__.py
azure/communication/sms/_generated/aio/operations/_sms_operations.py
azure/communication/sms/_generated/models/__init__.py
azure/communication/sms/_generated/models/_azure_communication_sms_service_enums.py
azure/communication/sms/_generated/models/_models.py
azure/communication/sms/_generated/models/_models_py3.py
azure/communication/sms/_generated/operations/__init__.py
azure/communication/sms/_generated/operations/_sms_operations.py
azure/communication/sms/_models/__init__.py
azure/communication/sms/_models/_models.py
azure/communication/sms/_models/_models_py3.py
azure/communication/sms/_shared/__init__.py
azure/communication/sms/_shared/auth_policy_utils.py
azure/communication/sms/_shared/models.py
azure/communication/sms/_shared/policy.py
azure/communication/sms/_shared/user_credential.py
azure/communication/sms/_shared/user_credential_async.py
azure/communication/sms/_shared/utils.py
azure/communication/sms/_shared/utils_async.py
azure/communication/sms/aio/__init__.py
azure/communication/sms/aio/_sms_client_async.py
azure_communication_sms-1.1.0.dist-info/LICENSE
azure_communication_sms-1.1.0.dist-info/METADATA
azure_communication_sms-1.1.0.dist-info/WHEEL
azure_communication_sms-1.1.0.dist-info/top_level.txt
azure_communication_sms-1.1.0.dist-info/RECORD
