Metadata-Version: 2.1
Name: azure-communication-sms
Version: 1.1.0
Summary: Microsoft Azure Communication SMS Client Library for Python
Home-page: https://github.com/Azure/azure-sdk-for-python
Author: Microsoft Corporation
Author-email: azuresdkengsysadmins@microsoft.com
License: MIT License
Keywords: azure,azure sdk
Classifier: Development Status :: 5 - Production/Stable
Classifier: Programming Language :: Python
Classifier: Programming Language :: Python :: 3 :: Only
Classifier: Programming Language :: Python :: 3
Classifier: Programming Language :: Python :: 3.8
Classifier: Programming Language :: Python :: 3.9
Classifier: Programming Language :: Python :: 3.10
Classifier: Programming Language :: Python :: 3.11
Classifier: Programming Language :: Python :: 3.12
Classifier: License :: OSI Approved :: MIT License
Requires-Python: >=3.8
License-File: LICENSE
Requires-Dist: azure-core>=1.27.0
Requires-Dist: msrest>=0.7.1
Requires-Dist: typing-extensions; python_version < "3.8"
